<?xml version="1.0" encoding="utf-8"?>
<SoundBanksInfo Platform="Mac" BasePlatform="Mac" SchemaVersion="16" SoundBankVersion="145">
	<SoundBanks>
		<SoundBank Id="1376358074" Type="Event" GUID="{D23E66E6-43DA-4114-901C-C8A2B0828697}" Language="SFX" Hash="{FC6DF7CD-2E58-B73A-4C76-6CCFC9E6C107}">
			<ObjectPath>Play_Player_Block_Light</ObjectPath>
			<ShortName>Play_Player_Block_Light</ShortName>
			<Path>Event/Play_Player_Block_Light.bnk</Path>
			<Media>
				<File Id="27748016" Language="SFX" Streaming="false" Location="Loose">
					<ShortName>sfx_fighter1_combat_blocking_light_01.wav</ShortName>
					<Path>Media/27748016.wem</Path>
					<CachePath>SFX/sfx_fighter1_combat_blocking_light_01_10C4C929.wem</CachePath>
				</File>
				<File Id="76329243" Language="SFX" Streaming="false" Location="Loose">
					<ShortName>sfx_fighter1_combat_blocking_light_04.wav</ShortName>
					<Path>Media/76329243.wem</Path>
					<CachePath>SFX/sfx_fighter1_combat_blocking_light_04_10C4C929.wem</CachePath>
				</File>
				<File Id="176246137" Language="SFX" Streaming="false" Location="Loose">
					<ShortName>sfx_fighter1_combat_blocking_light_02.wav</ShortName>
					<Path>Media/176246137.wem</Path>
					<CachePath>SFX/sfx_fighter1_combat_blocking_light_02_10C4C929.wem</CachePath>
				</File>
				<File Id="202002167" Language="SFX" Streaming="false" Location="Loose">
					<ShortName>sfx_fighter1_combat_blocking_light_05.wav</ShortName>
					<Path>Media/202002167.wem</Path>
					<CachePath>SFX/sfx_fighter1_combat_blocking_light_05_10C4C929.wem</CachePath>
				</File>
				<File Id="591698946" Language="SFX" Streaming="false" Location="Loose">
					<ShortName>sfx_fighter1_combat_blocking_light_03.wav</ShortName>
					<Path>Media/591698946.wem</Path>
					<CachePath>SFX/sfx_fighter1_combat_blocking_light_03_10C4C929.wem</CachePath>
				</File>
				<File Id="788773747" Language="SFX" Streaming="false" Location="Loose">
					<ShortName>sfx_fighter1_combat_blocking_light_06.wav</ShortName>
					<Path>Media/788773747.wem</Path>
					<CachePath>SFX/sfx_fighter1_combat_blocking_light_06_10C4C929.wem</CachePath>
				</File>
			</Media>
			<Events>
				<Event Id="1376358074" Name="Play_Player_Block_Light" ObjectPath="\Events\Player\PlayerCombat\Play_Player_Block_Light" GUID="{D23E66E6-43DA-4114-901C-C8A2B0828697}" DurationType="OneShot" DurationMin="0.20314583" DurationMax="0.28066668">
					<MediaRefs>
						<MediaRef Id="27748016"/>
						<MediaRef Id="76329243"/>
						<MediaRef Id="176246137"/>
						<MediaRef Id="202002167"/>
						<MediaRef Id="591698946"/>
						<MediaRef Id="788773747"/>
					</MediaRefs>
				</Event>
			</Events>
		</SoundBank>
	</SoundBanks>
	<FileHash>{2D9AC94F-2785-2020-BA17-4CE627507675}</FileHash>
</SoundBanksInfo>
